{
  "empresas": [
    {
      "id": 1,
      "nombre": "CIP FP Batoi",
      "domicilio": "C/ Societat Unió Musical, 2",
      "localidad": "Alcoi",
      "contacto": "Juan Segura",
      "email": "jsegura@bolsa.lan"
    },
    {
      "id": 2,
      "nombre": "2&2 tu web",
      "domicilio": "C/ Rue del percebe, 13",
      "localidad": "Alcoi",
      "contacto": "Marta Pérez",
      "email": "mperez@dosydos.lan"
    }
  ],
  "alumnos": [],
  "ofertas": [
    {
      "id": 2,
      "empresa": 1,
      "nombre": "epeppepepeeppe",
      "contrato": "LAB",
      "contacto": "Juan Segura Alfonso",
      "email": "jsegura@bolssssssssa.lan"
    },
    {
      "id": 3,
      "empresa": "1",
      "nombre": "Hola",
      "contrato": "epepepe",
      "contacto": "JuanT",
      "email": "juanito@gmail.com"
    },
    {
      "id": 4,
      "empresa": 2,
      "nombre": "ejejejejejeeee",
      "contrato": "holalalala",
      "contacto": "epepeppepee",
      "email": "joseluis@gmail.com"
    }
  ]
}